{
  "ogmoVersion": "3.4.0",
  "width": 440,
  "height": 176,
  "offsetX": 0,
  "offsetY": 0,
  "values": {"music": "kitsune underpass", "background": "default", "sky": "underground", "fadeVariant": "circle", "goalMode": "normal"},
  "layers": [
    {
      "name": "entities",
      "_eid": "26712369",
      "offsetX": 0,
      "offsetY": 0,
      "gridCellWidth": 8,
      "gridCellHeight": 8,
      "gridCellsX": 55,
      "gridCellsY": 22,
      "entities": [
        {
          "name": "start point",
          "id": 0,
          "_eid": "26863091",
          "x": 16,
          "y": 152,
          "originX": 0,
          "originY": 0,
          "values": {"entrance": "walk"}
        },
        {
          "name": "rival npc",
          "id": 1,
          "_eid": "91931981",
          "x": 248,
          "y": 88,
          "originX": 0,
          "originY": 0,
          "flippedX": true,
          "values": {"variant": "hello"}
        },
        {"name": "demond", "id": 2, "_eid": "26736337", "x": 72, "y": 144, "originX": 0, "originY": 0},
        {"name": "demond", "id": 3, "_eid": "26736337", "x": 112, "y": 144, "originX": 0, "originY": 0},
        {"name": "demond", "id": 4, "_eid": "26736337", "x": 152, "y": 144, "originX": 0, "originY": 0},
        {
          "name": "plant",
          "id": 6,
          "_eid": "30502269",
          "x": 232,
          "y": 152,
          "originX": 0,
          "originY": 0,
          "values": {"variant": "cherry", "trapped": false, "gilded": false, "restorative": false}
        },
        {
          "name": "plant",
          "id": 7,
          "_eid": "30502269",
          "x": 192,
          "y": 152,
          "originX": 0,
          "originY": 0,
          "values": {"variant": "cherry", "trapped": false, "gilded": false, "restorative": false}
        },
        {
          "name": "plant",
          "id": 8,
          "_eid": "30502269",
          "x": 0,
          "y": 152,
          "originX": 0,
          "originY": 0,
          "values": {"variant": "cherry", "trapped": false, "gilded": false, "restorative": false}
        },
        {
          "name": "plant",
          "id": 9,
          "_eid": "30502269",
          "x": 32,
          "y": 152,
          "originX": 0,
          "originY": 0,
          "values": {"variant": "cherry", "trapped": false, "gilded": false, "restorative": false}
        },
        {
          "name": "arrow shooter",
          "id": 10,
          "_eid": "55385650",
          "x": 400,
          "y": 56,
          "originX": 0,
          "originY": 0,
          "flippedX": true,
          "values": {"cycleOffset": 0}
        }
      ]
    },
    {
      "name": "tiles",
      "_eid": "26593690",
      "offsetX": 0,
      "offsetY": 0,
      "gridCellWidth": 8,
      "gridCellHeight": 8,
      "gridCellsX": 55,
      "gridCellsY": 22,
      "tileset": "world4",
      "data2D": [
        [-1, -1, -1, -1, -1, -1, -1, -1, -1, -1, -1, -1, -1, -1, -1, -1, -1, -1, -1, -1, -1, -1, -1, -1, -1, -1, -1, -1, -1, -1, -1, -1, -1, -1, -1, -1, -1, -1, -1, -1, -1, -1, -1, -1, -1, -1, -1, -1, -1, -1, -1, 33, 33, -1, -1],
        [-1, -1, -1, -1, -1, -1, -1, -1, -1, -1, -1, -1, -1, -1, -1, -1, -1, -1, -1, -1, -1, -1, -1, -1, -1, -1, -1, -1, -1, -1, -1, -1, -1, -1, -1, -1, -1, -1, -1, -1, -1, -1, -1, -1, -1, -1, -1, -1, -1, -1, -1, 33, 33, -1, -1],
        [-1, -1, -1, -1, -1, -1, -1, -1, -1, -1, -1, -1, -1, -1, -1, -1, -1, -1, -1, -1, -1, -1, -1, -1, -1, -1, -1, -1, -1, -1, -1, -1, -1, -1, -1, -1, -1, -1, -1, -1, -1, -1, -1, -1, -1, -1, -1, -1, -1, -1, -1, 33, 33, -1, -1],
        [-1, -1, -1, -1, -1, -1, -1, -1, -1, -1, -1, -1, -1, -1, -1, -1, -1, -1, -1, -1, -1, -1, -1, -1, -1, -1, -1, -1, -1, -1, -1, -1, -1, -1, -1, -1, -1, -1, -1, -1, -1, -1, -1, -1, -1, -1, -1, -1, -1, -1, -1, 33, 33, -1, -1],
        [-1, -1, -1, -1, -1, -1, -1, -1, -1, -1, -1, -1, -1, -1, -1, -1, -1, -1, -1, -1, -1, -1, -1, -1, -1, -1, -1, -1, -1, -1, -1, -1, -1, -1, -1, -1, -1, -1, -1, -1, -1, -1, -1, -1, -1, -1, -1, -1, -1, -1, -1, 33, 33, -1, -1],
        [-1, -1, -1, -1, -1, -1, -1, -1, -1, -1, -1, -1, -1, -1, -1, -1, -1, -1, -1, -1, -1, -1, -1, -1, -1, -1, -1, -1, -1, -1, 17, 17, 17, 17, 17, 17, 17, 17, 17, 17, 17, 17, 17, 25, 25, 25, -1, -1, -1, -1, -1, 33, 33, -1, -1],
        [-1, -1, -1, -1, 2, -1, -1, -1, -1, -1, -1, -1, -1, -1, -1, -1, -1, -1, -1, -1, -1, -1, -1, -1, -1, -1, -1, -1, -1, -1, 33, 33, 33, 33, 33, 33, 33, 33, 33, 33, 33, 33, 33, 33, 33, 34, -1, -1, -1, -1, -1, 26, 33, -1, -1],
        [-1, 99, 99, 99, 99, 99, 99, 99, 99, 99, 99, 99, 99, 99, 99, 99, 99, 99, 99, 99, 99, 99, 99, 99, 99, 99, 99, 99, 99, 99, 33, 33, 33, 33, 33, 33, 33, 33, 33, 33, 33, 33, 33, 33, 33, 34, -1, -1, -1, -1, -1, 25, 26, -1, -1],
        [-1, -1, -1, -1, -1, -1, -1, -1, -1, -1, -1, -1, -1, -1, -1, -1, -1, -1, -1, -1, -1, -1, -1, -1, -1, -1, -1, -1, -1, -1, 26, 26, 33, 33, 26, 33, 26, 26, 26, 26, 26, 26, 26, 26, 26, 25, -1, -1, -1, -1, -1, -1, 25, 25, 26],
        [-1, -1, -1, -1, -1, -1, -1, -1, -1, -1, -1, -1, -1, -1, -1, -1, -1, -1, -1, -1, -1, -1, -1, -1, -1, -1, -1, -1, -1, -1, -1, -1, 26, 26, 26, 26, 26, -1, -1, -1, -1, -1, -1, -1, -1, -1, -1, -1, -1, -1, -1, -1, -1, -1, -1],
        [-1, -1, -1, -1, -1, -1, -1, -1, -1, -1, -1, -1, -1, -1, -1, -1, -1, -1, -1, -1, -1, -1, -1, -1, -1, -1, -1, -1, -1, -1, -1, -1, -1, -1, 39, -1, -1, -1, -1, -1, -1, -1, -1, -1, -1, -1, -1, -1, -1, -1, -1, -1, -1, -1, -1],
        [-1, -1, -1, -1, -1, -1, -1, -1, -1, -1, -1, -1, -1, -1, -1, -1, -1, -1, -1, -1, -1, -1, -1, -1, -1, -1, -1, -1, -1, -1, -1, -1, -1, -1, 55, -1, -1, -1, -1, -1, -1, -1, -1, -1, -1, -1, -1, -1, -1, -1, -1, -1, -1, -1, -1],
        [-1, -1, -1, -1, -1, -1, -1, -1, -1, -1, -1, -1, -1, -1, -1, -1, -1, -1, -1, -1, -1, -1, -1, -1, -1, -1, -1, -1, -1, -1, -1, 16, 17, 17, 17, 17, 17, 17, 17, 25, 99, 99, 99, 99, 99, 26, 17, 17, 17, 25, 25, 25, 26, 26, 25],
        [-1, -1, -1, -1, -1, -1, -1, -1, -1, -1, -1, -1, -1, -1, -1, -1, -1, -1, -1, -1, -1, -1, -1, -1, -1, -1, -1, -1, -1, -1, -1, 25, 33, 33, 33, 33, 33, 33, 33, 26, -1, -1, -1, -1, -1, 25, 33, 33, 33, 33, 33, 33, 33, 33, 33],
        [-1, -1, -1, -1, -1, -1, -1, -1, -1, -1, -1, -1, -1, -1, -1, -1, -1, -1, -1, -1, -1, -1, -1, -1, -1, -1, -1, -1, -1, -1, -1, -1, 26, 25, 33, 33, 33, 33, 33, 25, -1, -1, -1, -1, -1, 32, 33, 33, 33, 33, 33, 33, 33, 33, 33],
        [-1, -1, -1, -1, -1, -1, -1, -1, -1, -1, -1, -1, -1, -1, -1, -1, -1, -1, -1, -1, -1, -1, -1, -1, -1, -1, -1, -1, -1, -1, -1, -1, -1, 26, 33, 26, 26, 25, 25, 26, -1, -1, -1, -1, -1, 32, 33, 33, 33, 33, 33, 33, 33, 33, 33],
        [-1, -1, -1, -1, -1, -1, -1, -1, -1, -1, -1, -1, -1, -1, -1, -1, -1, -1, -1, -1, -1, -1, -1, -1, -1, -1, -1, -1, -1, -1, -1, -1, -1, 23, 26, 33, -1, -1, -1, -1, -1, -1, -1, -1, -1, 32, 33, 33, 33, 33, 33, 33, 33, 33, 33],
        [-1, -1, -1, -1, -1, -1, -1, -1, -1, -1, -1, -1, -1, -1, -1, -1, -1, -1, -1, -1, -1, -1, -1, -1, -1, -1, -1, -1, -1, -1, -1, -1, -1, 26, 26, 25, -1, -1, -1, -1, -1, -1, -1, -1, -1, 32, 33, 33, 33, 33, 33, 33, 33, 33, 33],
        [-1, -1, -1, -1, -1, -1, -1, -1, -1, -1, -1, -1, -1, -1, -1, -1, -1, -1, -1, -1, -1, -1, -1, -1, -1, -1, -1, -1, -1, -1, -1, -1, -1, -1, 39, -1, -1, -1, -1, -1, -1, -1, -1, -1, -1, 32, 33, 33, 33, 33, 33, 33, 33, 33, 33],
        [-1, -1, -1, -1, -1, -1, -1, -1, 52, 53, 54, -1, -1, 52, 53, 54, -1, -1, 52, 53, 54, -1, -1, -1, -1, -1, 1, 1, -1, -1, -1, -1, -1, 1, 55, 1, -1, -1, -1, -1, -1, 1, 1, 1, -1, 25, 33, 33, 33, 33, 33, 33, 33, 33, 33],
        [17, 17, 17, 17, 17, 17, 17, 17, 17, 17, 17, 17, 17, 17, 17, 17, 17, 17, 17, 17, 17, 17, 17, 17, 17, 17, 17, 17, 17, 17, 17, 17, 17, 25, 26, 26, 17, 26, 25, 25, 17, 17, 17, 17, 17, 26, 33, 33, 33, 33, 33, 33, 33, 33, 33],
        [33, 33, 33, 33, 33, 33, 33, 33, 33, 33, 33, 33, 33, 33, 33, 33, 33, 33, 33, 33, 33, 33, 33, 33, 33, 33, 33, 33, 33, 33, 33, 33, 33, 17, 33, 33, 33, 33, 17, 33, 33, 33, 33, 33, 33, 33, 33, 33, 33, 33, 33, 33, 33, 33, 33]
      ],
      "exportMode": 0,
      "arrayMode": 1
    },
    {
      "name": "background tiles",
      "_eid": "58656142",
      "offsetX": 0,
      "offsetY": 0,
      "gridCellWidth": 8,
      "gridCellHeight": 8,
      "gridCellsX": 55,
      "gridCellsY": 22,
      "tileset": "world4",
      "data2D": [
        [-1, -1, -1, -1, -1, -1, -1, -1, -1, -1, -1, -1, -1, -1, -1, -1, -1, -1, -1, -1, -1, -1, -1, -1, -1, -1, -1, -1, -1, -1, -1, -1, -1, -1, -1, -1, -1, -1, -1, -1, -1, -1, -1, -1, -1, -1, -1, -1, -1, -1, -1, -1, -1, -1, -1],
        [-1, -1, -1, -1, -1, -1, -1, -1, -1, -1, -1, -1, -1, -1, -1, -1, -1, -1, -1, -1, -1, -1, -1, -1, -1, -1, -1, -1, -1, -1, -1, -1, -1, -1, -1, -1, -1, -1, -1, -1, -1, -1, -1, -1, -1, -1, -1, -1, -1, -1, -1, -1, -1, -1, -1],
        [-1, -1, -1, -1, -1, -1, -1, -1, -1, -1, -1, -1, -1, -1, -1, -1, -1, -1, -1, -1, -1, -1, -1, -1, -1, -1, -1, -1, -1, -1, -1, -1, -1, -1, -1, -1, -1, -1, -1, -1, -1, -1, -1, -1, -1, -1, -1, -1, -1, -1, -1, -1, -1, -1, -1],
        [-1, -1, -1, -1, -1, -1, -1, -1, -1, -1, -1, -1, -1, -1, -1, -1, -1, -1, -1, -1, -1, -1, -1, -1, -1, -1, -1, -1, -1, -1, -1, -1, -1, -1, -1, -1, -1, -1, -1, -1, -1, -1, -1, -1, -1, -1, -1, -1, -1, -1, -1, -1, -1, -1, -1],
        [-1, -1, -1, -1, -1, -1, -1, -1, -1, -1, -1, -1, -1, -1, -1, -1, -1, -1, -1, -1, -1, -1, -1, -1, -1, -1, -1, -1, -1, -1, -1, -1, -1, -1, -1, -1, -1, -1, -1, -1, -1, -1, -1, -1, -1, -1, -1, -1, -1, -1, -1, -1, -1, -1, -1],
        [-1, -1, -1, -1, -1, -1, -1, -1, -1, -1, -1, -1, -1, -1, -1, -1, -1, -1, -1, -1, -1, -1, -1, -1, -1, -1, -1, -1, -1, -1, -1, -1, -1, -1, -1, -1, -1, -1, -1, -1, -1, -1, -1, -1, -1, -1, -1, -1, -1, -1, -1, -1, -1, -1, -1],
        [-1, -1, -1, -1, -1, -1, -1, -1, -1, -1, -1, -1, -1, -1, -1, -1, -1, -1, -1, -1, -1, -1, -1, -1, -1, -1, -1, -1, -1, -1, -1, -1, -1, -1, -1, -1, -1, -1, -1, -1, -1, -1, -1, -1, -1, -1, -1, -1, -1, -1, -1, -1, -1, -1, -1],
        [-1, -1, -1, -1, -1, -1, -1, -1, -1, -1, -1, -1, -1, -1, -1, -1, -1, -1, -1, -1, -1, -1, -1, -1, -1, -1, -1, -1, -1, -1, -1, -1, -1, -1, -1, -1, -1, -1, -1, -1, -1, -1, -1, -1, -1, -1, -1, -1, -1, -1, -1, -1, -1, -1, -1],
        [-1, -1, -1, -1, -1, -1, -1, -1, -1, -1, -1, -1, -1, -1, -1, -1, -1, -1, -1, -1, -1, -1, -1, -1, -1, -1, -1, -1, -1, -1, -1, -1, -1, -1, -1, -1, -1, -1, -1, -1, -1, -1, -1, -1, -1, -1, -1, -1, -1, -1, -1, -1, -1, -1, -1],
        [-1, -1, -1, -1, -1, -1, -1, -1, -1, -1, -1, -1, -1, -1, -1, -1, -1, -1, -1, -1, -1, -1, -1, -1, -1, -1, -1, -1, -1, -1, -1, -1, -1, -1, -1, -1, -1, 33, 0, 33, 0, 0, 0, 33, 49, 25, -1, -1, -1, -1, -1, -1, -1, -1, -1],
        [-1, -1, -1, -1, -1, -1, -1, -1, -1, -1, -1, -1, -1, -1, -1, -1, -1, -1, -1, -1, -1, -1, -1, -1, -1, -1, -1, -1, -1, -1, -1, -1, -1, 25, 49, 49, 33, 33, 33, 0, 0, 33, 33, 49, 48, 25, -1, -1, -1, -1, -1, -1, -1, -1, -1],
        [-1, -1, -1, -1, -1, -1, -1, -1, -1, -1, -1, -1, -1, -1, -1, -1, -1, -1, -1, -1, -1, -1, -1, -1, -1, -1, -1, -1, -1, -1, -1, -1, -1, 25, 48, 49, 49, 33, 33, 33, 0, 33, 49, 48, 48, 25, -1, -1, -1, -1, 58, 58, 58, 58, 58],
        [-1, -1, -1, -1, -1, -1, -1, -1, -1, -1, -1, -1, -1, -1, -1, -1, -1, -1, -1, -1, -1, -1, -1, -1, -1, -1, -1, -1, -1, -1, -1, -1, -1, -1, -1, -1, -1, -1, -1, -1, 0, 0, 0, 0, 0, -1, -1, -1, -1, -1, -1, -1, -1, -1, -1],
        [-1, -1, -1, -1, -1, -1, -1, -1, -1, -1, -1, -1, -1, -1, -1, -1, -1, -1, -1, -1, -1, -1, -1, -1, -1, -1, -1, -1, -1, -1, -1, -1, -1, -1, -1, -1, -1, -1, -1, -1, 0, 33, 0, 0, 0, -1, -1, -1, -1, -1, -1, -1, -1, -1, -1],
        [-1, -1, -1, -1, -1, -1, -1, -1, -1, -1, -1, -1, -1, -1, -1, -1, -1, -1, -1, -1, -1, -1, -1, -1, -1, -1, -1, -1, -1, -1, -1, -1, -1, -1, -1, -1, -1, -1, -1, -1, 0, 0, 0, 33, 0, -1, -1, -1, -1, -1, -1, -1, -1, -1, -1],
        [-1, -1, -1, -1, -1, -1, -1, -1, -1, -1, -1, -1, -1, -1, -1, -1, -1, -1, -1, -1, -1, -1, -1, -1, -1, -1, -1, -1, -1, -1, -1, -1, 25, -1, -1, -1, -1, -1, -1, -1, 0, 33, 0, 0, 0, -1, -1, -1, -1, -1, -1, -1, -1, -1, -1],
        [-1, -1, -1, -1, -1, -1, -1, -1, -1, -1, -1, -1, -1, -1, -1, -1, -1, -1, -1, -1, -1, -1, -1, -1, -1, -1, -1, -1, -1, -1, -1, -1, 25, -1, -1, -1, 0, 0, 0, 0, 0, 0, 0, 0, 0, 0, -1, -1, -1, -1, -1, -1, -1, -1, -1],
        [-1, -1, -1, -1, -1, -1, -1, -1, -1, -1, -1, -1, -1, -1, -1, -1, -1, -1, -1, -1, -1, -1, -1, -1, -1, -1, -1, -1, -1, -1, -1, -1, -1, 25, -1, -1, 0, 0, 0, 33, 0, 0, 0, 0, 33, 0, 0, 0, -1, -1, -1, -1, -1, -1, -1],
        [-1, -1, -1, -1, -1, -1, -1, -1, -1, -1, -1, -1, -1, -1, -1, -1, -1, -1, -1, -1, -1, -1, -1, -1, -1, -1, -1, -1, -1, -1, -1, -1, -1, 25, 48, 33, 33, 0, 0, 0, 0, 33, 0, 0, 0, 0, 33, 0, 0, -1, -1, -1, -1, -1, -1],
        [-1, -1, -1, -1, -1, -1, -1, -1, -1, -1, -1, -1, -1, -1, -1, -1, -1, -1, -1, -1, -1, -1, -1, -1, -1, -1, -1, -1, 58, 58, 58, 58, 58, 25, 48, 49, 33, 33, 0, 0, 0, 0, 0, 0, 0, 0, 0, 0, -1, -1, -1, -1, -1, -1, -1],
        [-1, -1, -1, -1, -1, -1, -1, -1, -1, -1, -1, -1, -1, -1, -1, -1, -1, -1, -1, -1, -1, -1, -1, -1, -1, -1, -1, -1, -1, -1, -1, -1, -1, -1, -1, -1, -1, -1, -1, -1, -1, -1, -1, -1, -1, -1, -1, -1, -1, -1, -1, -1, -1, -1, -1],
        [-1, -1, -1, -1, -1, -1, -1, -1, -1, -1, -1, -1, -1, -1, -1, -1, -1, -1, -1, -1, -1, -1, -1, -1, -1, -1, -1, -1, -1, -1, -1, -1, -1, -1, -1, -1, -1, -1, -1, -1, -1, -1, -1, -1, -1, -1, -1, -1, -1, -1, -1, -1, -1, -1, -1]
      ],
      "exportMode": 0,
      "arrayMode": 1
    }
  ]
}